{
  "build_id": "BUILD-038",
  "generated_at": "2026-04-11T23:20:56.393595+00:00",
  "lm_ok": true,
  "summary": {
    "what_built": "This module creates a health endpoint to check the status of a database.",
    "problem": "It solves the problem of monitoring database operational status.",
    "files": [
      "draft_module.py",
      "draft_notes.md"
    ],
    "risk": "Medium risk because it only supports SQLite and lacks integration with a web framework.",
    "validation": "The code was checked for syntax errors and basic functionality.",
    "on_apply": "When the operator clicks Apply, the new health endpoint code will be added to the specified path in the repository.",
    "uncertainty": "It is uncertain how this will perform in a live environment, especially with different database types.",
    "target_path": "app/routes/database_health.py"
  }
}